kneading_orbital_graph/__init__.py
kneading_orbital_graph/inverse_section.py
kneading_orbital_graph/orbital_graph.py
kneading_orbital_graph/subshift.py
kneading_orbital_graph-1.0.4.dist-info/LICENSE.txt
kneading_orbital_graph-1.0.4.dist-info/METADATA
kneading_orbital_graph-1.0.4.dist-info/WHEEL
kneading_orbital_graph-1.0.4.dist-info/top_level.txt
kneading_orbital_graph-1.0.4.dist-info/RECORD
