Metadata-Version: 2.1
Name: kneading-orbital-graph
Version: 1.0.4
Home-page: https://gitlab.com/dmartinez05/kneading_orbital_graph
License: Apache-2.0
Classifier: License :: OSI Approved :: Apache Software License
License-File: LICENSE.txt
Requires-Dist: networkx
Requires-Dist: matplotlib
Requires-Dist: scipy
